libboost_regex.so
libsplitsnt.so
libsegmentor.so.0.2.0
libsrl.so.0.0.1
libboost_smart_ptr.so
libboost_regex.so.1.61
libmaxent.so.0.0.1
libboost_serialization.so
libmaxent.so
libner.so.0.0.2
libboost_smart_ptr.so.1.61
libsrl.so
libpostagger.so.0.0.3
libpostagger.so
libboost_program_options.so.1.61
libboost_serialization.so.1.61
libboost_program_options.so
libparser.so.0.0.1
libner.so
libbase_shared_lib.so
libparser.so
libsegmentor.so
libsplitsnt.so.0.0.1
pyltp.cpython-310-i386-linux-gnu.so
pyltp-0.4.0.dist-info/METADATA
pyltp-0.4.0.dist-info/top_level.txt
pyltp-0.4.0.dist-info/WHEEL
pyltp-0.4.0.dist-info/RECORD
