Metadata-Version: 2.1
Name: pyltp
Version: 0.4.0
Summary: pyltp: the python extension for LTP 3
Home-page: https://github.com/HIT-SCIR/pyltp
Author: Yijia Liu, Zixiang Xu, Yang Liu, Yunlong Feng
Author-email: ylfeng@ir.hit.edu.cn
Classifier: Development Status :: 4 - Beta
Classifier: Intended Audience :: Developers
Classifier: Intended Audience :: Science/Research
Classifier: License :: OSI Approved :: MIT License
Classifier: Programming Language :: Python :: 2
Classifier: Programming Language :: Python :: 2.6
Classifier: Programming Language :: Python :: 2.7
Classifier: Programming Language :: Python :: 3
Classifier: Programming Language :: Python :: 3.2
Classifier: Programming Language :: Python :: 3.3
Classifier: Programming Language :: Python :: 3.4
Classifier: Programming Language :: Python :: 3.5
Classifier: Programming Language :: Python :: 3.6
Classifier: Programming Language :: Python :: 3.7
Classifier: Programming Language :: Python :: 3.8
Classifier: Topic :: Software Development
Classifier: Topic :: Software Development :: Libraries :: Python Modules
Classifier: Topic :: Scientific/Engineering
Classifier: Topic :: Scientific/Engineering :: Information Analysis
Classifier: Topic :: Text Processing :: Linguistic
Requires-Python: >=3.6
Provides-Extra: test
Requires-Dist: pytest (>=6.0) ; extra == 'test'
